desolation/__init__.py
desolation/context.py
desolation/evaluate.py
desolation-2024.9.0.dist-info/LICENSE
desolation-2024.9.0.dist-info/WHEEL
desolation-2024.9.0.dist-info/METADATA
desolation-2024.9.0.dist-info/RECORD
